banxico_sie/__init__.py
banxico_sie/client.py
banxico_sie/enums.py
banxico_sie/exceptions.py
banxico_sie_xp-0.1.0.dist-info/licenses/LICENSE
banxico_sie_xp-0.1.0.dist-info/METADATA
banxico_sie_xp-0.1.0.dist-info/WHEEL
banxico_sie_xp-0.1.0.dist-info/top_level.txt
banxico_sie_xp-0.1.0.dist-info/RECORD
