Metadata-Version: 2.4
Name: banxico-sie-xp
Version: 0.1.0
Summary: Cliente Python para consultar tipos de cambio del SIE de Banxico
Author-email: Oswaldo PE <osperez.trabajo@gmail.com>
License: MIT
Project-URL: Homepage, https://github.com/tuusuario/banxico-sie
Project-URL: Repository, https://github.com/tuusuario/banxico-sie
Project-URL: Issues, https://github.com/tuusuario/banxico-sie/issues
Project-URL: Documentation, https://github.com/tuusuario/banxico-sie#readme
Keywords: banxico,sie,forex,exchange-rate,mexico,tipo-cambio
Classifier: Development Status :: 4 - Beta
Classifier: Intended Audience :: Developers
Classifier: Intended Audience :: Financial and Insurance Industry
Classifier: License :: OSI Approved :: MIT License
Classifier: Programming Language :: Python :: 3
Classifier: Programming Language :: Python :: 3.8
Classifier: Programming Language :: Python :: 3.9
Classifier: Programming Language :: Python :: 3.10
Classifier: Programming Language :: Python :: 3.11
Classifier: Programming Language :: Python :: 3.12
Classifier: Topic :: Office/Business :: Financial
Requires-Python: >=3.8
License-File: LICENSE
Requires-Dist: requests>=2.28.0
Requires-Dist: python-dateutil>=2.8.0
Provides-Extra: dev
Requires-Dist: pytest>=7.0.0; extra == "dev"
Requires-Dist: pytest-cov>=4.0.0; extra == "dev"
Requires-Dist: black>=22.0.0; extra == "dev"
Requires-Dist: flake8>=5.0.0; extra == "dev"
Requires-Dist: mypy>=1.0.0; extra == "dev"
Dynamic: license-file
